questdb_writer/__init__.py
questdb_writer/awsglue_questdb_writer.py
awsglue_questdb_writer-0.0.2.dist-info/LICENSE
awsglue_questdb_writer-0.0.2.dist-info/METADATA
awsglue_questdb_writer-0.0.2.dist-info/WHEEL
awsglue_questdb_writer-0.0.2.dist-info/top_level.txt
awsglue_questdb_writer-0.0.2.dist-info/RECORD
