Metadata-Version: 2.1
Name: awsglue-questdb-writer
Version: 0.0.2
Summary: A simple writing utility for writing to QuestDB from PySpark / AWS Glue using Line Protocol and Sockets
Home-page: https://github.com/Tymlez/awsglue-questdb-writer
Author: Dan Voyce
Author-email: dan.voyce+pypi@tymlez.com
License: UNKNOWN
Project-URL: Bug Tracker, https://github.com/Tymlez/awsglue-questdb-writer/issues
Platform: UNKNOWN
Classifier: Programming Language :: Python :: 3.6
Classifier: Programming Language :: Python :: 3.7
Classifier: Programming Language :: Python :: 3.8
Classifier: License :: OSI Approved :: MIT License
Classifier: Operating System :: OS Independent
Requires-Python: >=3.6
License-File: LICENSE
